odoo/addons/confirmation_wizard/README.rst
odoo/addons/confirmation_wizard/__init__.py
odoo/addons/confirmation_wizard/__manifest__.py
odoo/addons/confirmation_wizard/i18n/confirmation_wizard.pot
odoo/addons/confirmation_wizard/i18n/it.po
odoo/addons/confirmation_wizard/readme/CONTRIBUTORS.rst
odoo/addons/confirmation_wizard/readme/DESCRIPTION.rst
odoo/addons/confirmation_wizard/readme/USAGE.rst
odoo/addons/confirmation_wizard/security/ir.model.access.csv
odoo/addons/confirmation_wizard/static/description/icon.png
odoo/addons/confirmation_wizard/static/description/index.html
odoo/addons/confirmation_wizard/tests/__init__.py
odoo/addons/confirmation_wizard/tests/test_confirmation_wizard.py
odoo/addons/confirmation_wizard/wizard/__init__.py
odoo/addons/confirmation_wizard/wizard/confirmation_wizard.py
odoo/addons/confirmation_wizard/wizard/confirmation_wizard.xml
odoo_addon_confirmation_wizard-16.0.1.0.0.7.dist-info/METADATA
odoo_addon_confirmation_wizard-16.0.1.0.0.7.dist-info/WHEEL
odoo_addon_confirmation_wizard-16.0.1.0.0.7.dist-info/top_level.txt
odoo_addon_confirmation_wizard-16.0.1.0.0.7.dist-info/RECORD
